filehashs2df/README.MD
filehashs2df/__init__.py
filehashs2df/requirements.txt
filehashs2df/thirdparty.json
filehashs2df-0.10.dist-info/LICENSE.rst
filehashs2df-0.10.dist-info/METADATA
filehashs2df-0.10.dist-info/WHEEL
filehashs2df-0.10.dist-info/top_level.txt
filehashs2df-0.10.dist-info/RECORD
