Metadata-Version: 2.1
Name: filehashs2df
Version: 0.10
Summary: hashes files in the specified folder and its subfolders
Home-page: https://github.com/hansalemaos/filehashs2df
Author: Johannes Fischer
Author-email: aulasparticularesdealemaosp@gmail.com
License: MIT
Keywords: hash,dataframe
Classifier: Development Status :: 4 - Beta
Classifier: Programming Language :: Python :: 3 :: Only
Classifier: Programming Language :: Python :: 3.10
Classifier: Topic :: Software Development :: Libraries :: Python Modules
Classifier: Topic :: Utilities
License-File: LICENSE.rst
Requires-Dist: arrayhascher
Requires-Dist: list-all-files-recursively
Requires-Dist: numpy
Requires-Dist: pandas
